WeComMessage/WeComMessage.py
WeComMessage/__init__.py
wecommessage-1.0.3.dist-info/METADATA
wecommessage-1.0.3.dist-info/WHEEL
wecommessage-1.0.3.dist-info/top_level.txt
wecommessage-1.0.3.dist-info/RECORD
